<?xml version="1.0" encoding="UTF-8"?>
<window>
	<defaultcontrol>9000</defaultcontrol>
	<backgroundcolor>background</backgroundcolor>
	<controls>
		<control type="button" id="20000">
			<include>HiddenObject</include>
			<animation effect="fade" time="300" start="100" end="0">Focus</animation>
			<onfocus>SetFocus(2000)</onfocus>
			<onclick>noop</onclick>
			<visible allowhiddenfocus="true">Control.HasFocus(20000)</visible>
		</control>
		<control type="button" id="20001">
			<include>HiddenObject</include>
			<animation effect="fade" time="300" start="100" end="0">Focus</animation>
			<onfocus>SetFocus(2000)</onfocus>
			<onclick>noop</onclick>
			<visible allowhiddenfocus="true">Control.HasFocus(20001)</visible>
		</control>
		<include>DefaultBackground</include>
		
		
		<control type="image">
			<depth>DepthBackground</depth>
			<description>Normal Default Background Image</description>
			<include>BackgroundDimensions</include>
			<aspectratio>scale</aspectratio>
			<texture fallback="special://skin/backgrounds/SKINDEFAULT.jpg">$INFO[Skin.CurrentTheme,special://skin/backgrounds/,.jpg]</texture>
			<include>VisibleFadeEffect</include>
			<visible>true</visible>
		</control>
		
	</controls>
</window>
